openframe/__init__.py
openframe/audio.py
openframe/element.py
openframe/image.py
openframe/scene.py
openframe/shape.py
openframe/text.py
openframe/util.py
openframe/video.py
openframe-0.0.15.dist-info/METADATA
openframe-0.0.15.dist-info/WHEEL
openframe-0.0.15.dist-info/top_level.txt
openframe-0.0.15.dist-info/RECORD
