Metadata-Version: 2.4
Name: openframe
Version: 0.0.15
Summary: Python-native video editing toolkit that combines text, image, video, and audio layers.
Author-email: Keisuke Miyamoto <aichiboyhighschool@gmail.com>
License: MIT
Keywords: video editing,Python
Requires-Python: >=3.10
Requires-Dist: av
Requires-Dist: numpy
Requires-Dist: Pillow
Requires-Dist: tqdm
